skorplandgpt_enterprise/__init__.py
skorplandgpt_enterprise/enterprise_callbacks/callback_controls.py
skorplandgpt_enterprise/enterprise_callbacks/example_logging_api.py
skorplandgpt_enterprise/enterprise_callbacks/generic_api_callback.py
skorplandgpt_enterprise/enterprise_callbacks/llama_guard.py
skorplandgpt_enterprise/enterprise_callbacks/llm_guard.py
skorplandgpt_enterprise/enterprise_callbacks/pagerduty/pagerduty.py
skorplandgpt_enterprise/enterprise_callbacks/secret_detection.py
skorplandgpt_enterprise/enterprise_callbacks/secrets_plugins/__init__.py
skorplandgpt_enterprise/enterprise_callbacks/secrets_plugins/adafruit.py
skorplandgpt_enterprise/enterprise_callbacks/secrets_plugins/adobe.py
skorplandgpt_enterprise/enterprise_callbacks/secrets_plugins/age_secret_key.py
skorplandgpt_enterprise/enterprise_callbacks/secrets_plugins/airtable_api_key.py
skorplandgpt_enterprise/enterprise_callbacks/secrets_plugins/algolia_api_key.py
skorplandgpt_enterprise/enterprise_callbacks/secrets_plugins/alibaba.py
skorplandgpt_enterprise/enterprise_callbacks/secrets_plugins/asana.py
skorplandgpt_enterprise/enterprise_callbacks/secrets_plugins/atlassian_api_token.py
skorplandgpt_enterprise/enterprise_callbacks/secrets_plugins/authress_access_key.py
skorplandgpt_enterprise/enterprise_callbacks/secrets_plugins/beamer_api_token.py
skorplandgpt_enterprise/enterprise_callbacks/secrets_plugins/bitbucket.py
skorplandgpt_enterprise/enterprise_callbacks/secrets_plugins/bittrex.py
skorplandgpt_enterprise/enterprise_callbacks/secrets_plugins/clojars_api_token.py
skorplandgpt_enterprise/enterprise_callbacks/secrets_plugins/codecov_access_token.py
skorplandgpt_enterprise/enterprise_callbacks/secrets_plugins/coinbase_access_token.py
skorplandgpt_enterprise/enterprise_callbacks/secrets_plugins/confluent.py
skorplandgpt_enterprise/enterprise_callbacks/secrets_plugins/contentful_api_token.py
skorplandgpt_enterprise/enterprise_callbacks/secrets_plugins/databricks_api_token.py
skorplandgpt_enterprise-0.1.20.dist-info/METADATA
skorplandgpt_enterprise-0.1.20.dist-info/WHEEL
skorplandgpt_enterprise-0.1.20.dist-info/licenses/LICENSE.md
skorplandgpt_enterprise-0.1.20.dist-info/RECORD
