Metadata-Version: 2.4
Name: skorplandgpt-enterprise
Version: 0.1.20
Summary: Package for SkorplandGPT Enterprise features
License-File: LICENSE.md
Author: skorpland
Requires-Python: >=3.8, !=2.7.*, !=3.0.*, !=3.1.*, !=3.2.*, !=3.3.*, !=3.4.*, !=3.5.*, !=3.6.*, !=3.7.*
Classifier: Programming Language :: Python :: 3
Classifier: Programming Language :: Python :: 3.9
Classifier: Programming Language :: Python :: 3.10
Classifier: Programming Language :: Python :: 3.11
Classifier: Programming Language :: Python :: 3.12
Classifier: Programming Language :: Python :: 3.13
Classifier: Programming Language :: Python :: 3.14
Project-URL: Documentation, https://skorpland.com/platform
Project-URL: Homepage, https://skorpland.com
Project-URL: Repository, https://github.com/skorpland/skorplandgpt
Project-URL: documentation, https://skorpland.com/platform
Project-URL: homepage, https://skorpland.com
Project-URL: repository, https://github.com/skorpland/skorplandgpt
